{"cameraMode":{"drawMode":0,"name":"Shaded","section":"Shading Mode"},"sceneLighting":true,"audioPlay":false,"sceneViewState":{"m_AlwaysRefresh":false,"showFog":true,"showSkybox":true,"showFlares":true,"showImageEffects":true,"showParticleSystems":true,"showVisualEffectGraphs":true,"m_FxEnabled":true},"in2DMode":false,"pivot":{"x":-0.16553059220314027,"y":0.051144830882549289,"z":0.06906009465456009},"rotation":{"x":0.12087539583444596,"y":-0.02143992856144905,"z":0.0026113202329725029,"w":0.9924330711364746},"size":6.290004730224609,"orthographic":false}